teletgcf/__init__.py
teletgcf/bot/.env
teletgcf/bot/__init__.py
teletgcf/bot/live_bot.py
teletgcf/bot/utils.py
teletgcf/cli.py
teletgcf/config.py
teletgcf/const.py
teletgcf/live.py
teletgcf/past.py
teletgcf/plugins/__init__.py
teletgcf/plugins/filter.py
teletgcf/plugins/format.py
teletgcf/plugins/mark.py
teletgcf/plugins/ocr.py
teletgcf/plugins/replace.py
teletgcf/storage.py
teletgcf/teletgcf_user.session
teletgcf/utils.py
teletgcf-0.2.13.post0.dist-info/entry_points.txt
teletgcf-0.2.13.post0.dist-info/LICENSE
teletgcf-0.2.13.post0.dist-info/WHEEL
teletgcf-0.2.13.post0.dist-info/METADATA
teletgcf-0.2.13.post0.dist-info/RECORD
