Metadata-Version: 2.1
Name: teletgcf
Version: 0.2.13.post0
Summary: The ultimate tool to automate custom telegram message forwarding.
Home-page: https://github.com/jabrapatel800/teletgcf
License: MIT
Author: jabrapatel800
Author-email: jabrapatel800@gmail.com
Requires-Python: >=3.8,<4.0
Classifier: License :: OSI Approved :: MIT License
Classifier: Programming Language :: Python :: 3
Classifier: Programming Language :: Python :: 3.8
Classifier: Programming Language :: Python :: 3.9
Classifier: Programming Language :: Python :: 3.10
Requires-Dist: Pillow (>=8.1.2,<9.0.0)
Requires-Dist: PyYAML (>=5.4.1,<6.0.0)
Requires-Dist: Telethon (==1.25.0)
Requires-Dist: aiohttp (>=3.7.4,<4.0.0)
Requires-Dist: cryptg (>=0.2.post2,<0.3)
Requires-Dist: hachoir (>=3.1.2,<4.0.0)
Requires-Dist: pydantic (>=1.8.1,<2.0.0)
Requires-Dist: pyfiglet (>=0.8.post1,<0.9)
Requires-Dist: pytesseract (>=0.3.7,<0.4.0)
Requires-Dist: python-dotenv (>=0.17.0,<0.18.0)
Requires-Dist: requests (>=2.25.1,<3.0.0)
Requires-Dist: rich (>=10.3.0,<11.0.0)
Requires-Dist: tg-login (>=0.0.2,<0.0.3)
Requires-Dist: typer (>=0.3.2,<0.4.0)
Requires-Dist: verlat (>=0.1.0,<0.2.0)
Requires-Dist: watermark.py (>=0.0.3,<0.0.4)
Project-URL: Documentation, https://github.com/jabrapatel800/teletgcf/wiki
Project-URL: Repository, https://github.com/jabrapatel800/teletgcf
